Metadata-Version: 2.1
Name: one-cycle-tf
Version: 0.0.1
Summary: Tensorflow implementation of one cycle policy.
Home-page: UNKNOWN
Author: Denis Tananaev
Author-email: d.d.tananaev@gmail.com
License: UNKNOWN
Platform: UNKNOWN
Classifier: Programming Language :: Python :: 3
Classifier: License :: OSI Approved :: MIT License
Classifier: Operating System :: OS Independent
Requires-Python: >=3.6
